{
  "updated": "2026-04-19T09:00:00+09:00",
  "entries": [
    {"time": "4/19 06:00", "score": 68, "judge": "買い検討"},
    {"time": "4/19 00:00", "score": 65, "judge": "買い検討"},
    {"time": "4/18 18:00", "score": 71, "judge": "買い検討"},
    {"time": "4/18 12:00", "score": 69, "judge": "買い検討"},
    {"time": "4/18 06:00", "score": 62, "judge": "買い検討"},
    {"time": "4/18 00:00", "score": 58, "judge": "中立"},
    {"time": "4/17 18:00", "score": 55, "judge": "中立"},
    {"time": "4/17 12:00", "score": 52, "judge": "中立"},
    {"time": "4/17 06:00", "score": 48, "judge": "中立"},
    {"time": "4/17 00:00", "score": 44, "judge": "中立"},
    {"time": "4/16 18:00", "score": 41, "judge": "中立"},
    {"time": "4/16 12:00", "score": 38, "judge": "売り検討"}
  ]
}
